LICENSE
MANIFEST.in
README.md
setup.py
tap_autodesk_bim_360/__init__.py
tap_autodesk_bim_360/client.py
tap_autodesk_bim_360/discover.py
tap_autodesk_bim_360/endpoints.py
tap_autodesk_bim_360/sync.py
tap_autodesk_bim_360.egg-info/PKG-INFO
tap_autodesk_bim_360.egg-info/SOURCES.txt
tap_autodesk_bim_360.egg-info/dependency_links.txt
tap_autodesk_bim_360.egg-info/entry_points.txt
tap_autodesk_bim_360.egg-info/requires.txt
tap_autodesk_bim_360.egg-info/top_level.txt
tap_autodesk_bim_360/schemas/business_units.json
tap_autodesk_bim_360/schemas/checklists.json
tap_autodesk_bim_360/schemas/folder_contents.json
tap_autodesk_bim_360/schemas/issues.json
tap_autodesk_bim_360/schemas/projects.json