Metadata-Version: 1.1
Name: tap-autodesk-bim-360
Version: 0.0.1
Summary: Singer.io tap for extracting data from the Autodesk Forge BIM 360 API
Home-page: UNKNOWN
Author: UNKNOWN
Author-email: UNKNOWN
License: UNKNOWN
Platform: UNKNOWN
Classifier: Programming Language :: Python :: 3 :: Only
